signal_notification/__init__.py
signal_notification/admin.py
signal_notification/apps.py
signal_notification/models.py
signal_notification/notify_handlers.py
signal_notification/notify_manager.py
signal_notification/notify_media.py
signal_notification/views.py
signal_notification/migrations/0001_initial.py
signal_notification/migrations/__init__.py
django_signal_notification-0.0.1.dist-info/LICENSE
django_signal_notification-0.0.1.dist-info/METADATA
django_signal_notification-0.0.1.dist-info/WHEEL
django_signal_notification-0.0.1.dist-info/top_level.txt
django_signal_notification-0.0.1.dist-info/RECORD
