Metadata-Version: 2.1
Name: django-signal-notification
Version: 0.0.1
Summary: django app to send notifications using signals
Home-page: https://github.com/pprolancer/django-signal-notification
Author: PProlancer
Author-email: pprolancer@gmail.com
License: Apache License
Keywords: django,notification,signal
Platform: UNKNOWN
Classifier: License :: OSI Approved :: MIT License
Classifier: Environment :: Web Environment
Classifier: Framework :: Django
Classifier: Intended Audience :: Developers
Classifier: Operating System :: OS Independent
Classifier: Programming Language :: Python :: 3
Classifier: Programming Language :: Python :: 3.4
Classifier: Programming Language :: Python :: 3.5
Classifier: Programming Language :: Python :: 3.6
Classifier: Programming Language :: Python :: 3.7
Classifier: Programming Language :: Python :: 3.8
Classifier: Programming Language :: Python :: 3 :: Only
Classifier: Topic :: Internet :: WWW/HTTP
Classifier: Topic :: Internet :: WWW/HTTP :: Dynamic Content
Classifier: Topic :: Software Development
Classifier: Topic :: Software Development :: Libraries :: Application Frameworks
Requires-Python: >=3.4
Requires-Dist: django (>=2.0)
Requires-Dist: jsonfield
Requires-Dist: requests
Requires-Dist: cerberus
Requires-Dist: django-sendsms
